macast/.version
macast/__init__.py
macast/gui.py
macast/macast.py
macast/plugin.py
macast/protocol.py
macast/renderer.py
macast/server.py
macast/ssdp.py
macast/utils.py
macast/assets/avatar.png
macast/assets/element-ui@2.15.7.css
macast/assets/element-ui@2.15.7.js
macast/assets/icon.icns
macast/assets/icon.ico
macast/assets/icon.png
macast/assets/menu_dark.png
macast/assets/menu_dark_large.png
macast/assets/menu_light.png
macast/assets/menu_light_large.png
macast/assets/vue-resource@1.5.3.js
macast/assets/vue@2.6.14.js
macast/xml/AVTransport.xml
macast/xml/ConnectionManager.xml
macast/xml/Description.xml
macast/xml/RenderingControl.xml
macast/xml/SinkProtocolInfo.csv
macast/xml/setting.html
macast2-0.1.7.dist-info/licenses/LICENSE
macast_renderer/__init__.py
macast_renderer/mpv.py
macast2-0.1.7.dist-info/METADATA
macast2-0.1.7.dist-info/WHEEL
macast2-0.1.7.dist-info/entry_points.txt
macast2-0.1.7.dist-info/top_level.txt
macast2-0.1.7.dist-info/RECORD
