Metadata-Version: 2.4
Name: macast2
Version: 0.1.7
Summary: a DLNA Media Renderer
Home-page: https://github.com/isdkz/Macast2
Author: isdkz
Author-email: isdkz@outlook.com
License: GPL3
Keywords: mpv,dlna,renderer
Platform: MacOS X
Platform: Windows
Platform: POSIX
Classifier: Topic :: Multimedia :: Sound/Audio
Classifier: Topic :: Multimedia :: Video
Classifier: Programming Language :: Python :: 3
Classifier: Programming Language :: Python :: 3.6
Classifier: Programming Language :: Python :: 3.7
Classifier: Programming Language :: Python :: 3.8
Classifier: Programming Language :: Python :: 3.9
Classifier: Operating System :: MacOS :: MacOS X
Classifier: Operating System :: Microsoft :: Windows :: Windows NT/2000
Classifier: Operating System :: POSIX
Requires-Python: >=3.6
License-File: LICENSE
Requires-Dist: requests
Requires-Dist: appdirs
Requires-Dist: cherrypy
Requires-Dist: lxml
Requires-Dist: psutil
Requires-Dist: pywin32
Requires-Dist: packaging
Requires-Dist: pillow
Requires-Dist: pyperclip
Requires-Dist: pystray
Dynamic: author
Dynamic: author-email
Dynamic: classifier
Dynamic: description
Dynamic: description-content-type
Dynamic: home-page
Dynamic: keywords
Dynamic: license
Dynamic: license-file
Dynamic: platform
Dynamic: requires-dist
Dynamic: requires-python
Dynamic: summary
